axe_playwright_python/__init__.py
axe_playwright_python/async_playwright.py
axe_playwright_python/axe.min.js
axe_playwright_python/base.py
axe_playwright_python/sync_playwright.py
axe_playwright_python/violations.txt
axe_playwright_python-0.1.6.dist-info/LICENSE
axe_playwright_python-0.1.6.dist-info/WHEEL
axe_playwright_python-0.1.6.dist-info/METADATA
axe_playwright_python-0.1.6.dist-info/RECORD
