Metadata-Version: 2.1
Name: axe-playwright-python
Version: 0.1.6
Summary: Automated web accessibility testing using axe-core engine and Playwright.
Keywords: accessibility,axe,axe-core,playwright
Author-email: Pamela Fox <pamela.fox@gmail.com>
Requires-Python: >=3.8
Classifier: Programming Language :: Python
Classifier: Programming Language :: Python :: 3
Classifier: Programming Language :: Python :: 3.8
Classifier: Programming Language :: Python :: 3.9
Classifier: Programming Language :: Python :: 3.10
Classifier: Programming Language :: Python :: 3.11
Classifier: Programming Language :: Python :: 3.12
Classifier: Programming Language :: Python :: 3.13
Classifier: Topic :: Adaptive Technologies
Classifier: Topic :: Software Development
Classifier: Topic :: Software Development :: Quality Assurance
Classifier: Topic :: Software Development :: Testing
Requires-Dist: playwright >= 1.36.0
Requires-Dist: pytest == 7.4.0 ; extra == "dev"
Requires-Dist: pytest-cov == 4.1.0 ; extra == "dev"
Requires-Dist: pytest-playwright == 0.3.3 ; extra == "dev"
Requires-Dist: pytest-asyncio == 0.21.1 ; extra == "dev"
Requires-Dist: mkdocs == 1.4.3 ; extra == "dev"
Requires-Dist: mkdocstrings == 0.22.0 ; extra == "dev"
Requires-Dist: mkdocs-material == 9.1.19 ; extra == "dev"
Requires-Dist: black == 23.7.0 ; extra == "dev"
Requires-Dist: ruff == 0.0.280 ; extra == "dev"
Requires-Dist: pre-commit == 3.3.3 ; extra == "dev"
Requires-Dist: flit ; extra == "dev"
Project-URL: Documentation, https://pamelafox.github.io/axe-playwright-python
Project-URL: GitHub, https://github.com/pamelafox/axe-playwright-python
Provides-Extra: dev
